{
  "app.name": "Digital Stokvel Banking",
  "app.welcome": "Welcome to your group",
  "payment.reminder.3days": "Your payment of {0} is due in 3 days",
  "payment.reminder.1day": "Your payment of {0} is due tomorrow",
  "payment.confirmation": "Payment of {0} received. Thank you!",
  "payment.receipt": "Receipt for your contribution of {0} to {1}",
  "payment.failed": "Your payment didn't go through this time—let's try again",
  "group.created": "Your group '{0}' has been created successfully",
  "group.member.invited": "{0} has been invited to join your group",
  "payout.initiated": "Payout of {0} has been initiated",
  "payout.completed": "Payout of {0} sent to {1}",
  "balance.current": "Your group balance is {0}",
  "interest.earned": "Interest earned this month: {0}",
  "error.general": "Something went wrong. Please try again.",
  "error.unauthorized": "You don't have permission to perform this action",
  "error.notfound": "The requested resource was not found",
  "error.validation": "Please check your information and try again",
  "error.badrequest": "We couldn't process that request—please check your information",
  "error.conflict": "That operation couldn't be completed right now—please try again",
  "error.database": "We couldn't save your changes this time—let's try again",
  "error.timeout": "The request took too long—please try again",
  "error.network": "We're having trouble connecting—please check your network",
  "error.title.badrequest": "Invalid Request",
  "error.title.unauthorized": "Unauthorized",
  "error.title.notfound": "Resource Not Found",
  "error.title.conflict": "Operation Failed",
  "error.title.server": "An Error Occurred",
  "notification.sms.invitation": "You're invited to join '{0}'! Contribution: R{1}. Use code {2} to join.",
  "notification.sms.contribution_confirmed": "We received your R{0} contribution to '{1}'. New balance: R{2}. Thank you for being part of the community!",
  "notification.sms.payment_reminder": "Friendly reminder: Your R{0} contribution to '{1}' is due on {2}. Thank you!",
  "notification.sms.payout_notification": "Good news! R{0} has been paid out to {1} from '{2}'.",
  "notification.push.invitation": "{0} invited you to join '{1}'",
  "notification.push.contribution_confirmed": "Your R{0} contribution to '{1}' was successful!",
  "notification.push.payment_reminder_3days": "Reminder: Your '{0}' contribution of R{1} is due in 3 days",
  "notification.push.payment_reminder_1day": "Urgent: Your '{0}' contribution of R{1} is due tomorrow",
  "notification.push.payment_reminder_generic": "Reminder: Your '{0}' contribution of R{1} is due soon",
  "notification.push.payout_notification": "Payout of R{0} to {1} from '{2}' completed successfully",
  "ussd.main.title": "Digital Stokvel",
  "ussd.main.pay": "Pay Contribution",
  "ussd.main.balance": "Check Balance",
  "ussd.main.transactions": "View Transactions",
  "ussd.main.language": "Change Language",
  "ussd.groups.title": "Select your group:",
  "ussd.language.title": "Choose language:",
  "ussd.balance.display": "{0}\nBalance: R{1}\nInterest: R{2}",
  "ussd.receipt.display": "Payment confirmed!\nAmount: R{0}\nGroup: {1}\nRef: {2}",
  "ussd.transactions.title": "Recent Transactions",
  "ussd.confirm": "Confirm",
  "ussd.cancel": "Cancel",
  "ussd.back": "Back",
  "ussd.next": "Next",
  "ussd.error.nogroups": "You are not a member of any group yet.",
  "ussd.error.notransactions": "No transactions found.",
  "ussd.error.invalid": "Invalid selection. Please try again.",
  "ussd.pay.confirm": "Pay R{1} to {0}?",
  "ussd.pay.enterpin": "Enter your 4-digit PIN:",
  "ussd.pay.invalidpin": "Invalid PIN. Transaction cancelled.",
  "ussd.pay.failed": "Payment failed. Please try again.",
  "ussd.cancelled": "Transaction cancelled."
}
